{
	"cmake" : 
	{
		"generator" : 
		{
			"multiConfig" : false,
			"name" : "Unix Makefiles"
		},
		"paths" : 
		{
			"cmake" : "/opt/homebrew/bin/cmake",
			"cpack" : "/opt/homebrew/bin/cpack",
			"ctest" : "/opt/homebrew/bin/ctest",
			"root" : "/opt/homebrew/share/cmake"
		},
		"version" : 
		{
			"isDirty" : false,
			"major" : 4,
			"minor" : 2,
			"patch" : 3,
			"string" : "4.2.3",
			"suffix" : ""
		}
	},
	"objects" : 
	[
		{
			"jsonFile" : "codemodel-v2-975eff1422b978a13220.json",
			"kind" : "codemodel",
			"version" : 
			{
				"major" : 2,
				"minor" : 9
			}
		},
		{
			"jsonFile" : "cache-v2-7678b170d4fbb0cd494c.json",
			"kind" : "cache",
			"version" : 
			{
				"major" : 2,
				"minor" : 0
			}
		},
		{
			"jsonFile" : "cmakeFiles-v1-7f7d56dc928a710b2e25.json",
			"kind" : "cmakeFiles",
			"version" : 
			{
				"major" : 1,
				"minor" : 1
			}
		},
		{
			"jsonFile" : "toolchains-v1-7a6f6b179cfd98362766.json",
			"kind" : "toolchains",
			"version" : 
			{
				"major" : 1,
				"minor" : 0
			}
		}
	],
	"reply" : 
	{
		"client-vscode" : 
		{
			"query.json" : 
			{
				"requests" : 
				[
					{
						"kind" : "cache",
						"version" : 2
					},
					{
						"kind" : "codemodel",
						"version" : 2
					},
					{
						"kind" : "toolchains",
						"version" : 1
					},
					{
						"kind" : "cmakeFiles",
						"version" : 1
					}
				],
				"responses" : 
				[
					{
						"jsonFile" : "cache-v2-7678b170d4fbb0cd494c.json",
						"kind" : "cache",
						"version" : 
						{
							"major" : 2,
							"minor" : 0
						}
					},
					{
						"jsonFile" : "codemodel-v2-975eff1422b978a13220.json",
						"kind" : "codemodel",
						"version" : 
						{
							"major" : 2,
							"minor" : 9
						}
					},
					{
						"jsonFile" : "toolchains-v1-7a6f6b179cfd98362766.json",
						"kind" : "toolchains",
						"version" : 
						{
							"major" : 1,
							"minor" : 0
						}
					},
					{
						"jsonFile" : "cmakeFiles-v1-7f7d56dc928a710b2e25.json",
						"kind" : "cmakeFiles",
						"version" : 
						{
							"major" : 1,
							"minor" : 1
						}
					}
				]
			}
		}
	}
}
